MANIFEST.in
README.md
setup.py
version.txt
radbm/__init__.py
radbm.egg-info/PKG-INFO
radbm.egg-info/SOURCES.txt
radbm.egg-info/dependency_links.txt
radbm.egg-info/top_level.txt
radbm/benchmarks/__init__.py
radbm/benchmarks/__main__.py
radbm/loaders/__init__.py
radbm/loaders/base.py
radbm/loaders/mnist.py
radbm/loaders/coco/__init__.py
radbm/loaders/coco/alteredcoco.py
radbm/loaders/coco/alterimages.py
radbm/metrics/__init__.py
radbm/metrics/hamming.py
radbm/metrics/oracle.py
radbm/metrics/sswr.py
radbm/search/__init__.py
radbm/search/base.py
radbm/search/gridsearch.py
radbm/search/mbsds.py
radbm/search/radius.py
radbm/search/elba/__init__.py
radbm/search/elba/base.py
radbm/search/elba/fbeta.py
radbm/search/elba/hashnet.py
radbm/search/elba/hbkl.py
radbm/search/elba/mihash.py
radbm/tests/__init__.py
radbm/tests/loaders_base.py
radbm/tests/metrics_hamming.py
radbm/tests/metrics_oracle.py
radbm/tests/metrics_sswr.py
radbm/tests/search_base.py
radbm/tests/search_elba_base.py
radbm/tests/search_elba_fbeta.py
radbm/tests/search_elba_hashnet.py
radbm/tests/search_elba_hbkl.py
radbm/tests/search_elba_mihash.py
radbm/tests/search_gridsearch.py
radbm/tests/search_mbsds.py
radbm/tests/search_radius.py
radbm/tests/utils.py
radbm/tests/utils_fetch.py
radbm/tests/utils_stats.py
radbm/tests/utils_time.py
radbm/tests/utils_torch.py
radbm/tests/utils_torch_color.py
radbm/tests/utils_torch_multi_bernoulli_log_arithmetic.py
radbm/tests/utils_torch_poisson_binomial.py
radbm/utils/__init__.py
radbm/utils/fetch.py
radbm/utils/notebook.py
radbm/utils/os.py
radbm/utils/gdrive/__init__.py
radbm/utils/gdrive/download.py
radbm/utils/gdrive/fileid.json
radbm/utils/stats/__init__.py
radbm/utils/stats/generators.py
radbm/utils/stats/hypergeometric.py
radbm/utils/time/__init__.py
radbm/utils/time/chronometer.py
radbm/utils/torch/__init__.py
radbm/utils/torch/color.py
radbm/utils/torch/messy.py
radbm/utils/torch/multi_bernoulli/__init__.py
radbm/utils/torch/multi_bernoulli/log_arithmetic.py
radbm/utils/torch/multi_bernoulli/poisson_binomial.py