Metadata-Version: 2.1
Name: radbm
Version: 2020.11.3
Summary: Rapid Access Database Benchmark
Home-page: https://github.com/duchesneaumathieu/radbm
Author: Mathieu Duchesneau
Author-email: duchesneau.mathieu@gmail.com
License: UNKNOWN
Platform: UNKNOWN
Classifier: Programming Language :: Python :: 3
Classifier: Intended Audience :: Science/Research
Classifier: License :: OSI Approved :: MIT License
Classifier: Operating System :: OS Independent
Requires-Python: >=3.6
